ml_pipeline_gen/__init__.py
ml_pipeline_gen/models.py
ml_pipeline_gen/parsers.py
ml_pipeline_gen/pipelines.py
ml_pipeline_gen/static/bin/cleanup.sh
ml_pipeline_gen/static/bin/run.local_train.sh
ml_pipeline_gen/static/orchestration/__init__.py
ml_pipeline_gen/static/orchestration/components/list_blobs.yaml
ml_pipeline_gen/static/trainer/__init__.py
ml_pipeline_gen/static/trainer/utils.py
ml_pipeline_gen/templates/kfp_pipeline.py
ml_pipeline_gen/templates/setup.py
ml_pipeline_gen/templates/sklearn_inputs.py
ml_pipeline_gen/templates/sklearn_model.py
ml_pipeline_gen/templates/sklearn_task.py
ml_pipeline_gen/templates/tf_inputs.py
ml_pipeline_gen/templates/tf_model.py
ml_pipeline_gen/templates/tf_task.py
ml_pipeline_gen/templates/xgboost_inputs.py
ml_pipeline_gen/templates/xgboost_model.py
ml_pipeline_gen/templates/xgboost_task.py
ml_pipeline_gen-0.0.5.dist-info/LICENSE
ml_pipeline_gen-0.0.5.dist-info/METADATA
ml_pipeline_gen-0.0.5.dist-info/WHEEL
ml_pipeline_gen-0.0.5.dist-info/top_level.txt
ml_pipeline_gen-0.0.5.dist-info/RECORD
