Metadata-Version: 2.1
Name: ml-pipeline-gen
Version: 0.0.5
Summary: A tool for generating end-to-end pipelines on GCP.
Home-page: https://github.com/GoogleCloudPlatform/ml-pipeline-generator-python
Author: Michael Hu
Author-email: author@example.com
License: UNKNOWN
Platform: UNKNOWN
Classifier: Programming Language :: Python :: 3
Classifier: License :: OSI Approved :: Apache Software License
Classifier: Operating System :: OS Independent
Requires-Python: >=3.6
Requires-Dist: cloudml-hypertune
Requires-Dist: gcsfs
Requires-Dist: google-api-python-client
Requires-Dist: jinja2
Requires-Dist: joblib
Requires-Dist: kfp
Requires-Dist: pandas
Requires-Dist: pyyaml
Requires-Dist: scikit-learn
Requires-Dist: tensorflow (<2.0.0,>=0.14.0)
Requires-Dist: xgboost
